[{"id":0,"Nombre":"Demetrio Cansalmas","Departamento":"Drenaje de almas","Tlf":"654654654","EmailContact":"demetriocansalmas@hotmail.com","Ubicacion":"Alcafrán"},{"id":1,"Nombre":"La vieja del visillo","Departamento":"Espionaje","Tlf":"658854131","EmailContact":"marian23@gmail.com","Ubicacion":"Alcafrán"},{"id":2,"Nombre":"Juana de Arco","Departamento":"Linaje","Tlf":"01","EmailContact":"Noestoyloca@gmail.com","Ubicacion":"Castilla"},{"id":3,"Nombre":"Faker ","Departamento":"Idolos","Tlf":"6663476376","EmailContact":"elmejor@gmail.com","Ubicacion":"korea"},{"id":4,"Nombre":"Juan Carlos Camino ","Departamento":"EL TIRADOR DE PAIN GAMING","Tlf":"6566236","EmailContact":"top1draven@gmail.com","Ubicacion":"La grita del Invocador"},{"id":5,"Nombre":"Berengario el Trastorista","Departamento":"Agricultura y comercio.","Tlf":"987654321","EmailContact":"brerengariojuasjuas@gmail.com","Ubicacion":"Su tractor"},{"id":6,"Nombre":"Bartolomé Gómez Martín","Departamento":"Acosamiento de camioneros de la M30.","Tlf":"976356498","EmailContact":"bar_tolitos@gmail.com","Ubicacion":"Plató de lo que necesitas es amor"},{"id":7,"Nombre":"Ibai Llanos Garatea","Departamento":"Todos, ocupa mas de uno.","Tlf":"536253","EmailContact":"Ibai@gmail.com","Ubicacion":"Es la via lactea seguramente"},{"id":8,"Nombre":"Tía Catenaria","Departamento":"Reparto de alpargatas.","Tlf":"142549276","EmailContact":"latiacati@gmail.com","Ubicacion":"Casa del Cura de Alcafrán."}]
